titanfi/__init__.py
titanfi/judge.py
titanfi/adversarial/__init__.py
titanfi/adversarial/adversarial.py
titanfi/adversarial/tester.py
titanfi/agent/__init__.py
titanfi/agent/agent.py
titanfi/domains/__init__.py
titanfi/domains/code_generation.py
titanfi/domains/code_prompt_writer.py
titanfi/evolution/__init__.py
titanfi/evolution/evolution.py
titanfi/judge/__init__.py
titanfi/judge/judge.py
titanfi/llm/__init__.py
titanfi/llm/llm.py
titanfi/prompt_writer/__init__.py
titanfi/prompt_writer/prompt_writer.py
titanfi-0.1.1.dist-info/LICENSE
titanfi-0.1.1.dist-info/METADATA
titanfi-0.1.1.dist-info/WHEEL
titanfi-0.1.1.dist-info/top_level.txt
titanfi-0.1.1.dist-info/RECORD
